mine_mods
