Metadata-Version: 1.0
Name: minecraft-mods-downloader
Version: 0.6.1
Summary: Control minecraft mods download easily with this tool
Home-page: https://github.com/arruda/minecraft-mods-downloader
Author: Felipe Arruda Pontes
Author-email: contato@arruda.blog.br
License: MIT
Keywords: minecraft,download,mods,control
Platform: UNKNOWN
